LICENSE
NOTICE
README.rst
setup.py
bn254/__init__.py
bn254/big.py
bn254/bls.py
bn254/constants.py
bn254/curve.py
bn254/ecdh.py
bn254/ecp.py
bn254/ecp2.py
bn254/fp.py
bn254/fp12.py
bn254/fp2.py
bn254/fp4.py
bn254/mpin.py
bn254/pair.py
bn254.egg-info/PKG-INFO
bn254.egg-info/SOURCES.txt
bn254.egg-info/dependency_links.txt
bn254.egg-info/top_level.txt