Metadata-Version: 2.1
Name: bn254
Version: 0.1.2
Summary: Pure-Python library that implements operations over the BN(2,254) pairing-friendly curve.
Home-page: https://github.com/nthparty/bn254
Author: Wyatt Howe
Author-email: wyatt@nthparty.com
License: Apache License 2.0
License-File: LICENSE
License-File: NOTICE
